datapizza/modules/parsers/azure/__init__.py
datapizza/modules/parsers/azure/azure_parser.py
datapizza_ai_parsers_azure-0.0.5.dist-info/METADATA
datapizza_ai_parsers_azure-0.0.5.dist-info/WHEEL
datapizza_ai_parsers_azure-0.0.5.dist-info/RECORD
