Metadata-Version: 2.4
Name: datapizza-ai-parsers-azure
Version: 0.0.5
Summary: Azure Document Intelligence parser for the datapizza-ai framework
Author-email: Datapizza <datapizza@datapizza.tech>
License: MIT
Classifier: License :: OSI Approved :: MIT License
Classifier: Operating System :: OS Independent
Classifier: Programming Language :: Python :: 3
Requires-Python: <4,>=3.10.0
Requires-Dist: aiofiles>=24.1.0
Requires-Dist: azure-ai-documentintelligence<2.0.0,>=1.0.1
Requires-Dist: datapizza-ai-core<0.1.0,>=0.0.1
Requires-Dist: pillow>=11.3.0
Requires-Dist: pymupdf<2.0.0,>=1.25.4
